testrail/__init__.py
testrail/api.py
testrail/base.py
testrail/case.py
testrail/casetype.py
testrail/client.py
testrail/configuration.py
testrail/entry.py
testrail/helper.py
testrail/milestone.py
testrail/plan.py
testrail/priority.py
testrail/project.py
testrail/result.py
testrail/run.py
testrail/section.py
testrail/status.py
testrail/suite.py
testrail/template.py
testrail/test.py
testrail/user.py
testrail-0.3.15.dist-info/LICENSE.txt
testrail-0.3.15.dist-info/METADATA
testrail-0.3.15.dist-info/WHEEL
testrail-0.3.15.dist-info/top_level.txt
testrail-0.3.15.dist-info/RECORD
